Verilog/bright led---/brightled.v
module LED_Controller (
    input wire reset,
    input wire bright_up,
    input wire bright_down,
    output reg led
);

reg [2:0] brightness;

always @ (posedge reset)
begin
    brightness <= 3'b000; // Initialize brightness to the lowest level
end

always @ (*)
begin
    if (reset)
        led <= 1'b0; // Reset LED to off state
    else if (bright_up && brightness < 3'b111)
        brightness <= brightness + 1; // Increase brightness by 1 level
    else if (bright_down && brightness > 3'b000)
        brightness <= brightness - 1; // Decrease brightness by 1 level
end

always @ (*)
begin
    if (brightness > 0)
        led <= 1'b1; // Turn on LED if brightness is greater than 0
    else
        led <= 1'b0; // Turn off LED if brightness is 0
end

endmodule


module LED_Controller_tb;

reg reset, bright_up, bright_down;
wire led;

LED_Controller DUT (
    .reset(reset),
    .bright_up(bright_up),
    .bright_down(bright_down),
    .led(led)
);
initial begin
	$dumpfile("bright_led.vcd");
	$dumpvars();
    reset = 1'b1;
    #10 reset = 1'b0;
    #20 bright_up = 1'b1;
    #20 bright_up = 1'b0;
    #20 bright_up = 1'b1;
    #20 bright_up = 1'b0;
    #20 bright_down = 1'b1;
    #20 bright_down = 1'b0;
    #20 bright_up = 1'b1;
    #20 bright_down = 1'b1;
    #20 reset = 1'b1;
    #10 reset = 1'b0;
    #20 bright_down = 1'b0;
    #20 $finish;
end
always @ (*) $monitor("LED: %b", led);
endmodule

Verilog/bright led---/bright_led.vcd
$date
	Fri Jun  2 13:52:19 2023
$end
$version
	Icarus Verilog
$end
$timescale
	1s
$end
$scope module LED_Controller_tb $end
$var wire 1 ! led $end
$var reg 1 " bright_down $end
$var reg 1 # bright_up $end
$var reg 1 $ reset $end
$scope module DUT $end
$var wire 1 " bright_down $end
$var wire 1 # bright_up $end
$var wire 1 $ reset $end
$var reg 3 % brightness [2:0] $end
$var reg 1 ! led $end
$upscope $end
$upscope $end
$enddefinitions $end
#0
$dumpvars
b0 %
1$
x#
x"
0!
$end
#10
0$
#30
1!
b111 %
1#
#50
0#
#70
0!
b0 %
1"
#90
0"
#110
1!
b111 %
1#
#130

b111 %
1#
#170

#110
1!
b111 &
1#
