Verilog/bright led---/signal.v
module Signal_Controller (
    input wire clk,
    input wire res,
    input wire button1,
    input wire button2,
    output reg signal
);

reg [6:0] count;
reg [6:0] calibrate_count;
reg [6:0] duration;

always @(posedge clk or posedge res) begin
    if (res)
        count <= 7'b0; // Reset count to 0
    else if (button1)
        count <= count + 1; // Increment count
    else if (button2)
        count <= count - 1; // Decrement count
end

always @(posedge clk or posedge res) begin
    if (res)
        duration <= 7'b0; // Reset duration to 0
    else if (button1 || button2)
        duration <= duration + 1; // Increment duration
end

always @(posedge clk) begin
    if (duration >= 7'b1111101) // 125 in decimal (approximately 1 second)
        calibrate_count <= count;
end

always @(posedge clk or posedge res) begin
    if (res)
        signal <= 1'b0; // Reset signal to 0
    else if (duration >= 7'b1111101) // 125 in decimal (approximately 1 second)
        signal <= calibrate_count[0]; // Calibrate signal to the least significant bit of calibrate_count
end

endmodule

module Signal_Controller_tb;

reg clk, res, button1, button2;
wire signal;

Signal_Controller DUT (
    .clk(clk),
    .res(res),
    .button1(button1),
    .button2(button2),
    .signal(signal)
);

initial begin
    $monitor("Signal: %b", signal);
    clk = 1'b0;
    forever #5 clk = ~clk;
end

initial begin
$dumpfile("signal.vcd");
$dumpvars();

    res = 1'b1;
    button1 = 1'b0;
    button2 = 1'b0;
    #10 res = 1'b0;
    #20 button1 = 1'b1;
    #30 button1 = 1'b0;
    #20 button2 = 1'b1;
    #40 button2 = 1'b0;
    #100 $finish;
end

endmodule

Verilog/bright led---/signal.vcd
$date
	Fri Jun  2 14:05:29 2023
$end
$version
	Icarus Verilog
$end
$timescale
	1s
$end
$scope module Signal_Controller_tb $end
$var wire 1 ! signal $end
$var reg 1 " button1 $end
$var reg 1 # button2 $end
$var reg 1 $ clk $end
$var reg 1 % res $end
$scope module DUT $end
$var wire 1 " button1 $end
$var wire 1 # button2 $end
$var wire 1 $ clk $end
$var wire 1 % res $end
$var reg 7 & calibrate_count [6:0] $end
$var reg 7 ' count [6:0] $end
$var reg 7 ( duration [6:0] $end
$var reg 1 ! signal $end
$upscope $end
$upscope $end
$enddefinitions $end
#0
$dumpvars
b0 (
b0 '
bx &
1%
0$
0#
0"
0!
$end
#5
1$
#10
0$
0%
#15
1$
#20
0$
#25
1$
#30
0$
1"
#35
b1 '
b1 (
1$
#40
0$
#45
b10 (
b10 '
1$
#50
0$
#55
b11 '
b11 (
1$
#60
0$
0"
#65
1$
#70
0$
#75
1$
#80
0$
1#
#85
b100 (
b10 '
1$
#90
0$
#95
b1 '
b101 (
1$
#100
0$
#105
b110 (
b0 '
1$
#110
0$
#115
b1111111 '
b111 (
1$
#120
0$
0#
