Verilog/segment_2_buttons/debounce.v
module debounce (clk, rst, button, button_out);

input clk;
input rst;

input button;
output button_out;

reg  [17:0] counter;
wire [17:0] counter_nxt;
wire full;

assign full = (counter == 18'd250000);
assign counter_nxt = (button) ? (~full ? counter + {{17{1'b0}}, 1'b1} : 9'd250000) : {18{1'b0}};
assign button_out = full;

always @(posedge clk) begin
    if (rst) counter <= {18{1'b0}};
    else     counter <= counter_nxt;
end

endmodule

Verilog/segment_2_buttons/segmentbutton.v
module segment_display (
  input clk,
  input rst,
  input button_plus,
  input button_minus,
  output reg [6:0] segment
);
  reg [3:0] number;
  wire b_plus_out;
  wire b_minus_out;

  debounce debplus (
	  .clk(clk),
	  .rst(rst),
	  .button(button_plus),
	  .button_out(b_plus_out)
  );

  debounce debminus (
	  .clk(clk),
	  .rst(rst),
	  .button(button_minus),
	  .button_out(b_minus_out)
  );

  always @(posedge clk) begin
    if (rst) begin
      number <= 4'b0000;
      segment <= 7'b0000000;
    end
    else begin
      if (button_plus && !button_minus && number != 4'b1001)
        number <= number + 1;
      else if (button_minus && !button_plus && number != 4'b0000)
        number <= number - 1;
    end
  end

  always @(number) begin
    case(number)
      4'b0000: segment <= 7'b1000000;
      4'b0001: segment <= 7'b1111001;
      4'b0010: segment <= 7'b0100100;
      4'b0011: segment <= 7'b0110000;
      4'b0100: segment <= 7'b0011001;
      4'b0101: segment <= 7'b0010010;
      4'b0110: segment <= 7'b0000010;
      4'b0111: segment <= 7'b1111000;
      4'b1000: segment <= 7'b0000000;
      4'b1001: segment <= 7'b0011000;
      default: segment <= 7'b0000000;
    endcase
  end
endmodule

Verilog/segment_2_buttons/testbench.v
module segment_display_tb;

  reg clk;
  reg rst;
  reg button_plus;
  reg button_minus;
  wire [6:0] segment;

  segment_display dut (
    .clk(clk),
    .rst(rst),
    .button_plus(button_plus),
    .button_minus(button_minus),
    .segment(segment)
  );

  
  always #5 clk = ~clk;

  initial begin
	$dumpfile("segment2buttons.vcd");
	$dumpvars();
    clk = 0;
    rst = 1;
    button_plus = 0;
    button_minus = 0;
    #10 rst = 0; 


    #15 button_plus = 1; 
    #50 button_plus = 0;   
    #15 button_plus = 1; 
    #5 button_plus = 0;   
    #10 button_minus = 1; 
    #5 button_minus = 0;  
    #20 button_plus = 1;  
    #5 button_plus = 0;   


    #1000 $finish; 
  end

  always @(posedge clk) begin
    $display("Segment: %b", segment);
  end

endmodule

Verilog/segment_2_buttons/segment2buttons.vcd
$date
	Tue Jun  6 18:05:12 2023
$end
$version
	Icarus Verilog
$end
$timescale
	1s
$end
$scope module segment_display_tb $end
$var wire 7 ! segment [6:0] $end
$var reg 1 " button_minus $end
$var reg 1 # button_plus $end
$var reg 1 $ clk $end
$var reg 1 % rst $end
$scope module dut $end
$var wire 1 " button_minus $end
$var wire 1 # button_plus $end
$var wire 1 $ clk $end
$var wire 1 % rst $end
$var wire 1 & b_plus_out $end
$var wire 1 ' b_minus_out $end
$var reg 4 ( number [3:0] $end
$var reg 7 ) segment [6:0] $end
$scope module debminus $end
$var wire 1 " button $end
$var wire 1 ' button_out $end
$var wire 1 $ clk $end
$var wire 1 % rst $end
$var wire 1 * full $end
$var wire 18 + counter_nxt [17:0] $end
$var reg 18 , counter [17:0] $end
$upscope $end
$scope module debplus $end
$var wire 1 # button $end
$var wire 1 & button_out $end
$var wire 1 $ clk $end
$var wire 1 % rst $end
$var wire 1 - full $end
$var wire 18 . counter_nxt [17:0] $end
$var reg 18 / counter [17:0] $end
$upscope $end
$upscope $end
$upscope $end
$enddefinitions $end
#0
$dumpvars
bx /
b0 .
x-
bx ,
b0 +
x*
bx )
bx (
x'
x&
1%
0$
0#
0"
bx !
$end
#5
0&
0-
b0 /
0'
0*
b0 ,
b1 !
b1 )
b0 (
1$
#10
0$
0%
#15
1$
#20
0$
#25
b1 /
b10 .
1$
1#
#30
0$
#35
b10010000 .
1&
1-
b10 /
1$
#40
0$
#45
b1001111 !
b1001111 )
b10010001 .
0&
0-
b10010000 /
b1 (
1$
#50
0$
#55
b10010010 .
b10010001 /
1$
#60
0$
#65
b10010011 .
b10010010 /
1$
#70
0$
#75
b0 /
b0 .
1$
0#
#80
0$
#85
1$
#90
b1 .
0$
1#
#95
b0 .
1$
0#
#100
0$
#105
b1 ,
b10 +
1$
1"
#110
b0 +
0$
0"
#115
b0 ,
1$
#120
0$
#125
1$
#130
b1 .
0$
1#
#135
b0 .
1$
0#
